setup.py
relaxml/__init__.py
relaxml/converter.py
relaxml.egg-info/PKG-INFO
relaxml.egg-info/SOURCES.txt
relaxml.egg-info/dependency_links.txt
relaxml.egg-info/top_level.txt