Metadata-Version: 1.0
Name: relaxml
Version: 0.1.3
Summary: Converting XML to a dictionary should be easy -- and fast.
Home-page: http://github.com/zachwill/relaxml
Author: Zach Williams
Author-email: hey@zachwill.com
License: MIT
Platform: UNKNOWN
Classifier: Development Status :: 1 - Planning
Classifier: Intended Audience :: Developers
Classifier: Natural Language :: English
Classifier: License :: OSI Approved :: MIT License
Classifier: Programming Language :: Python
Classifier: Programming Language :: Python :: 2.6
Classifier: Programming Language :: Python :: 2.7
